[
    {
        "title": "Test App",
        "color": "yellow",
        "url": "http://localhost/",
        "detail": "Serialization is serious, localhost is local.",
        "action": "redirect"
    },
    {
        "title": "Google",
        "image": "http://localhost/vault/data/img/google.png",
        "url": "http://google.com/",
        "detail": "Always nice to have google right?",
        "action": "newtab"
    },
    {
        "title": "Facebook",
        "image": "https://upload.wikimedia.org/wikipedia/commons/thumb/7/7c/Facebook_New_Logo_%282015%29.svg/512px-Facebook_New_Logo_%282015%29.svg.png",
        "url": "http://facebook.com/",
        "detail": "Facebook social network. stalk 1 hour a day to feel better.",
        "action": "popup"
    },
    {
        "title": "Youtube",
        "image": "https://lh3.googleusercontent.com/Ned_Tu_ge6GgJZ_lIO_5mieIEmjDpq9kfgD05wapmvzcInvT4qQMxhxq_hEazf8ZsqA=s180",
        "detail": "Why bother watching trending ? Why not.",
        "action": "redirect"
    },
    {
        "title": "Amazon",
        "image": "http://images.frandroid.com/wp-content/uploads/2015/03/amazon_1-1000x364.jpg",
        "url": "http://amazon.com/",
        "detail": "Buy some stupid goods you don't need.",
        "action": "redirect"
    },
    {
        "title": "Google Drive",
        "image": "http://www.ghanalive.tv/wp-content/uploads/2017/09/Google-Drive-Logo.png",
        "url": "http://drive.google.com/",
        "detail": "What's on the cloud?",
        "action": "redirect"
    },
    {
        "title": "Trello",
        "image": "https://lh3.googleusercontent.com/z7oKSvTI-2ynS5bHggIctR9GVkS8sGKqpDlfCvgxLo0du7Az00u6XpJ0LLyvzBusW-Jd=s180",
        "url": "http://trello.com/",
        "detail": "Organize your mess for better handling.",
        "action": "redirect"
    },
    {
        "title": "Ebay",
        "detail": "10 Hours left for a $999 stephen hawkins hair?! Gotta bid!",
        "action": "redirect"
    }
]